quote0/__init__.py
quote0/cli.py
quote0/client.py
quote0/models.py
quote0/streamlit_components.py
quote0/utils.py
quote0-0.1.1.dist-info/METADATA
quote0-0.1.1.dist-info/WHEEL
quote0-0.1.1.dist-info/entry_points.txt
quote0-0.1.1.dist-info/licenses/LICENSE
quote0-0.1.1.dist-info/RECORD
