Metadata-Version: 2.4
Name: quote0
Version: 0.1.1
Summary: Python API client for Quote/0 display device
Project-URL: Repository, https://github.com/daviddwlee84/Quote0
Project-URL: Streamlit, https://quote0.streamlit.app/
Author: Da-Wei Lee
License-Expression: MIT
License-File: LICENSE
Keywords: api,display,iot,quote0
Classifier: Development Status :: 3 - Alpha
Classifier: Intended Audience :: Developers
Classifier: License :: OSI Approved :: MIT License
Classifier: Programming Language :: Python :: 3
Classifier: Programming Language :: Python :: 3.9
Classifier: Programming Language :: Python :: 3.10
Classifier: Programming Language :: Python :: 3.11
Classifier: Programming Language :: Python :: 3.12
Classifier: Programming Language :: Python :: 3.13
Requires-Python: >=3.9
Requires-Dist: matplotlib>=3.8.0
Requires-Dist: numpy>=1.26.0
Requires-Dist: pillow>=10.0.0
Requires-Dist: pydantic>=2.11.8
Requires-Dist: python-dotenv[cli]>=1.1.1
Requires-Dist: requests>=2.31.0
Requires-Dist: streamlit>=1.49.1
Requires-Dist: tyro>=0.9.31
Requires-Dist: watchdog>=6.0.0
